fixedfieldreader/__init__.py
fixedfieldreader/error.py
fixedfieldreader/fixedfieldreader.py
fixedfieldreader/fixedfieldreader_test.py
fixedfieldreader-1.0.0.dist-info/METADATA
fixedfieldreader-1.0.0.dist-info/RECORD
fixedfieldreader-1.0.0.dist-info/WHEEL
fixedfieldreader-1.0.0.dist-info/top_level.txt
